LICENSE
MANIFEST.in
README.rst
setup.py
Cahoots.egg-info/PKG-INFO
Cahoots.egg-info/SOURCES.txt
Cahoots.egg-info/dependency_links.txt
Cahoots.egg-info/entry_points.txt
Cahoots.egg-info/requires.txt
Cahoots.egg-info/top_level.txt
cahoots/__init__.py
cahoots/config.py
cahoots/data.py
cahoots/parser.py
cahoots/result.py
cahoots/util.py
cahoots/confidence/__init__.py
cahoots/confidence/normalizer.py
cahoots/confidence/normalizers/__init__.py
cahoots/confidence/normalizers/base.py
cahoots/confidence/normalizers/character.py
cahoots/confidence/normalizers/date.py
cahoots/confidence/normalizers/equation.py
cahoots/confidence/normalizers/number.py
cahoots/confidence/normalizers/phone.py
cahoots/data/prepositions.yaml
cahoots/parsers/__init__.py
cahoots/parsers/base.py
cahoots/parsers/boolean.py
cahoots/parsers/character.py
cahoots/parsers/date.py
cahoots/parsers/email.py
cahoots/parsers/equation.py
cahoots/parsers/name.py
cahoots/parsers/number.py
cahoots/parsers/phone.py
cahoots/parsers/uri.py
cahoots/parsers/location/__init__.py
cahoots/parsers/location/address.py
cahoots/parsers/location/coordinate.py
cahoots/parsers/location/landmark.py
cahoots/parsers/location/postalcode.py
cahoots/parsers/location/data/LICENSE
cahoots/parsers/location/data/city.sql
cahoots/parsers/location/data/city.txt.bz2
cahoots/parsers/location/data/country.csv.bz2
cahoots/parsers/location/data/country.sql
cahoots/parsers/location/data/landmark.csv.bz2
cahoots/parsers/location/data/landmark.sql
cahoots/parsers/location/data/location.sql
cahoots/parsers/location/data/location.sqlite.dist
cahoots/parsers/location/data/street_suffix.csv.bz2
cahoots/parsers/location/data/street_suffix.sql
cahoots/parsers/measurement/__init__.py
cahoots/parsers/measurement/units/imperial_area.yaml
cahoots/parsers/measurement/units/imperial_length.yaml
cahoots/parsers/measurement/units/imperial_mass.yaml
cahoots/parsers/measurement/units/imperial_temperature.yaml
cahoots/parsers/measurement/units/imperial_volume.yaml
cahoots/parsers/measurement/units/metric_area.yaml
cahoots/parsers/measurement/units/metric_length.yaml
cahoots/parsers/measurement/units/metric_mass.yaml
