Metadata-Version: 1.1
Name: Cahoots
Version: 0.5.2
Summary: A Text Comprehension Engine in Python.
Home-page: https://github.com/SerenitySoftwareLLC/cahoots
Author: Serenity Software
Author-email: hello@serenitysoftware.io
License: MIT
Platform: UNKNOWN
Classifier: Development Status :: 4 - Beta
Classifier: License :: OSI Approved :: MIT License
Classifier: Programming Language :: Python
Classifier: Programming Language :: Python :: 2
Classifier: Programming Language :: Python :: 2.7
Classifier: Programming Language :: Python :: 3
Classifier: Programming Language :: Python :: 3.4
Classifier: Topic :: Utilities
Classifier: Operating System :: MacOS
Classifier: Operating System :: POSIX :: Linux
